Workbook
Name aporte: Planilha1!$D$17
Name patrimonio: Planilha1!$D$20
Name qtd_anos: Planilha1!$D$18
Name rendimento_carteira: Planilha1!$D$13
Name taxa_mensal: Planilha1!$D$19

Sheet Planilha1
B11: CONFIGURAÇÕES
B12: Salário | D12: 7000
B13: Rendimento mensal estimado da Carteira | D13: 0.009
B14: Sugestão de Investimento (30% da renda) | D14: =D12*30% -> 2100
B16: INVESTIMENTO MENSAL
B17: Quanto inverstir por mês? | D17: 300
B18: Por quantos anos? | D18: 5
B19: Taxa de rendimento mensal estimada | D19: 0.01079
B20: Patrimônio acumulado estimado | D20: =FV(taxa_mensal,qtd_anos*12,aporte*-1) -> 25133.074
B21: Dividendos mensais estimados | D21: =patrimonio*rendimento_carteira -> 226.19767
B23: CENÁRIOS | D23: DIVIDENDOS
A24: 2 | B24: Patrimônio acumulado em 2 anos | C24: =FV($D$19,$A24*12,$D$17*-1) -> 8168.2882 | D24: =C24*rendimento_carteira -> 73.514594
A25: 3 | B25: Patrimônio acumulado em 3 anos | C25: =FV($D$19,$A25*12,$D$17*-1) -> 13112.512 | D25: =C25*rendimento_carteira -> 118.01261
A26: 4 | B26: Patrimônio acumulado em 4 anos | C26: =FV($D$19,$A26*12,$D$17*-1) -> 18736.306 | D26: =C26*rendimento_carteira -> 168.62675
A27: 5 | B27: Patrimônio acumulado em 5 anos | C27: =FV($D$19,$A27*12,$D$17*-1) -> 25133.074 | D27: =C27*rendimento_carteira -> 226.19767
A28: 6 | B28: Patrimônio acumulado em 6 anos | C28: =FV($D$19,$A28*12,$D$17*-1) -> 32409.06 | D28: =C28*rendimento_carteira -> 291.68154
A29: 7 | B29: Patrimônio acumulado em 7 anos | C29: =FV($D$19,$A29*12,$D$17*-1) -> 40685.11 | D29: =C29*rendimento_carteira -> 366.16599
A30: 8 | B30: Patrimônio acumulado em 8 anos | C30: =FV($D$19,$A30*12,$D$17*-1) -> 50098.68 | D30: =C30*rendimento_carteira -> 450.88812
A31: 9 | B31: Patrimônio acumulado em 9 anos | C31: =FV($D$19,$A31*12,$D$17*-1) -> 60806.118 | D31: =C31*rendimento_carteira -> 547.25506
A32: 10 | B32: Patrimônio acumulado em 10 anos | C32: =FV($D$19,$A32*12,$D$17*-1) -> 72985.264 | D32: =C32*rendimento_carteira -> 656.86737
A33: 11 | B33: Patrimônio acumulado em 11 anos | C33: =FV($D$19,$A33*12,$D$17*-1) -> 86838.399 | D33: =C33*rendimento_carteira -> 781.54559
A34: 12 | B34: Patrimônio acumulado em 12 anos | C34: =FV($D$19,$A34*12,$D$17*-1) -> 102595.61 | D34: =C34*rendimento_carteira -> 923.36047
A35: 13 | B35: Patrimônio acumulado em 13 anos | C35: =FV($D$19,$A35*12,$D$17*-1) -> 120518.6 | D35: =C35*rendimento_carteira -> 1084.6674
... A52: 30 | B52: Patrimônio acumulado em 30 anos | C52: =FV($D$19,$A52*12,$D$17*-1) -> 1296650.9 | D52: =C52*rendimento_carteira -> 11669.858
B54: PERFIL | C54: Moderado
B55: VALOR A SER INVESTIDO POR MÊS | C55: 300
B57: TIPO DE FII | C57: PERCENTUAL SUGERIDO | D57: VALORES
B58: PAPEL | C58: =VLOOKUP($C$54&" - "&B58,DADOS_PERFIL!$A:$D,4,FALSE) -> 0.35 | D58: =C58*$C$55 -> 105
B59: TIJOLO | C59: =VLOOKUP($C$54&" - "&B59,DADOS_PERFIL!$A:$D,4,FALSE) -> 0.4 | D59: =C59*$C$55 -> 120
B60: HÍBRIDOS | C60: =VLOOKUP($C$54&" - "&B60,DADOS_PERFIL!$A:$D,4,FALSE) -> 0.15 | D60: =C60*$C$55 -> 45
B61: FOF'S | C61: =VLOOKUP($C$54&" - "&B61,DADOS_PERFIL!$A:$D,4,FALSE) -> 0.1 | D61: =C61*$C$55 -> 30
B62: Desenvolvimento | C62: =VLOOKUP($C$54&" - "&B62,DADOS_PERFIL!$A:$D,4,FALSE) -> 0.05 | D62: =C62*$C$55 -> 15
B63: Hotelarias | C63: =VLOOKUP($C$54&" - "&B63,DADOS_PERFIL!$A:$D,4,FALSE) -> 0.06 | D63: =C63*$C$55 -> 18
B64: Total | D64: =SUM(D58:D61) -> 300

Sheet DADOS_PERFIL
A1: CHAVE | B1: PERFIL | C1: TIPO DE FII | D1: %
A2: =B2&" - "&C2 -> Conservador - PAPEL | B2: Conservador | C2: PAPEL | D2: 0.5
A3: =B3&" - "&C3 -> Conservador - TIJOLO | B3: Conservador | C3: TIJOLO | D3: 0.2
A4: =B4&" - "&C4 -> Conservador - HÍBRIDOS | B4: Conservador | C4: HÍBRIDOS | D4: 0.2
A5: =B5&" - "&C5 -> Conservador - FOF'S | B5: Conservador | C5: FOF'S | D5: 0.1
A6: =B6&" - "&C6 -> Conservador - DESENVOLVIMENTO | B6: Conservador | C6: DESENVOLVIMENTO | D6: 0.02
A7: =B7&" - "&C7 -> Conservador - HOTELARIAS | B7: Conservador | C7: HOTELARIAS | D7: 0.03
A8: =B8&" - "&C8 -> Moderado - PAPEL | B8: Moderado | C8: PAPEL | D8: 0.35
A9: =B9&" - "&C9 -> Moderado - TIJOLO | B9: Moderado | C9: TIJOLO | D9: 0.4
A10: =B10&" - "&C10 -> Moderado - HÍBRIDOS | B10: Moderado | C10: HÍBRIDOS | D10: 0.15
A11: =B11&" - "&C11 -> Moderado - FOF'S | B11: Moderado | C11: FOF'S | D11: 0.1
A12: =B12&" - "&C12 -> Moderado - DESENVOLVIMENTO | B12: Moderado | C12: DESENVOLVIMENTO | D12: 0.05
A13: =B13&" - "&C13 -> Moderado - HOTELARIAS | B13: Moderado | C13: HOTELARIAS | D13: 0.06
... A19: =B19&" - "&C19 -> Agressivo - HOTELARIAS | B19: Agressivo | C19: HOTELARIAS | D19: 0.08
